mysql_wrap/__init__.py
mysql_wrap/mysqlwrap.py
mysql_wrap-1.1.3.dist-info/METADATA
mysql_wrap-1.1.3.dist-info/WHEEL
mysql_wrap-1.1.3.dist-info/licenses/LICENSE
mysql_wrap-1.1.3.dist-info/RECORD
