Metadata-Version: 2.1
Name: mysql_wrap
Version: 1.1.3
Summary: Simple wrapper for common mysql queries, including utilities for pandas DataFrames
Project-URL: Homepage, https://github.com/henn-dt/MySQL-wrap
Project-URL: Bug Tracker, https://github.com/henn-dt/MySQL-wrap/issues
Author-email: emiliano lupo <emiliano.lupo@henn.com>
License-File: LICENSE
Keywords: mysql,pandas
Classifier: License :: Other/Proprietary License
Classifier: Operating System :: OS Independent
Classifier: Programming Language :: Python :: 3
Requires-Python: >=3.7
Requires-Dist: mysql-connector-python
Requires-Dist: pandas
